pytest_selenium_screenshot/__init__.py
pytest_selenium_screenshot/event_listener.py
pytest_selenium_screenshot/logger.py
pytest_selenium_screenshot/plugin.py
pytest_selenium_screenshot/utils.py
pytest_selenium_screenshot-1.0.0.dist-info/entry_points.txt
pytest_selenium_screenshot-1.0.0.dist-info/WHEEL
pytest_selenium_screenshot-1.0.0.dist-info/METADATA
pytest_selenium_screenshot-1.0.0.dist-info/RECORD
